LICENSE
MANIFEST.in
README.md
setup.py
101703088_topsis.egg-info/PKG-INFO
101703088_topsis.egg-info/SOURCES.txt
101703088_topsis.egg-info/dependency_links.txt
101703088_topsis.egg-info/entry_points.txt
101703088_topsis.egg-info/requires.txt
101703088_topsis.egg-info/top_level.txt
topsis/topsis.py