Metadata-Version: 2.1
Name: 101703088-topsis
Version: 1.0.6
Summary: A Python package to choose the best alternative from a finite set of decision alternatives.
Home-page: https://github.com/user/101703088-topsis
Author: Anurag Aggarwal
Author-email: agrawalanurag321@gmail.com
License: MIT
Download-URL: https://github.com/Anurag-Aggarwal/101703088-topsis/blob/master/topsis.py
Platform: UNKNOWN
Classifier: License :: OSI Approved :: MIT License
Classifier: Programming Language :: Python :: 3
Classifier: Programming Language :: Python :: 3.4
Classifier: Programming Language :: Python :: 3.5
Classifier: Programming Language :: Python :: 3.6
Classifier: Programming Language :: Python :: 3.7
